zerochan/__init__.py
zerochan/__main__.py
zerochan/c_exceptions.py
zerochan/dtypes.py
zerochan/lib.py
zerochan-0.5.0.dist-info/WHEEL
zerochan-0.5.0.dist-info/METADATA
zerochan-0.5.0.dist-info/RECORD
