Metadata-Version: 2.1
Name: zerochan
Version: 0.5.0
Summary: Python library and download cli util for https://www.zerochan.net
Home-page: https://github.com/kiriharu/zerochan
License: MIT
Keywords: zerochan,booru,parser,util,pics 
Author: kiriharu
Author-email: kiriharu@yandex.ru
Requires-Python: >=3.9,<4.0
Classifier: Development Status :: 5 - Production/Stable
Classifier: Environment :: Console
Classifier: License :: OSI Approved :: MIT License
Classifier: Natural Language :: Russian
Classifier: Programming Language :: Python :: 3
Classifier: Programming Language :: Python :: 3.10
Classifier: Programming Language :: Python :: 3.9
Classifier: Topic :: Utilities
Classifier: Typing :: Typed
Requires-Dist: beautifulsoup4 (>=4.9.3,<5.0.0)
Requires-Dist: requests (>=2.25.1,<3.0.0)
Project-URL: Repository, https://github.com/kiriharu/zerochan
